Metadata-Version: 2.1
Name: pulumi-gomigrate
Version: 1.0.2
Summary: UNKNOWN
Home-page: UNKNOWN
License: UNKNOWN
Platform: UNKNOWN
